impact/__init__.py
impact/sdk/__init__.py
impact/sdk/context.py
impact/sdk/decorators.py
impact/sdk/impact.py
impact/sdk/otel.py
impact/sdk/registry.py
impact-0.6.0.dist-info/METADATA
impact-0.6.0.dist-info/WHEEL
impact-0.6.0.dist-info/top_level.txt
impact-0.6.0.dist-info/RECORD
