Metadata-Version: 2.4
Name: impact
Version: 0.6.0
Summary: Impact AI SDK (OTel-native, GenAI semantic conventions)
Author: Impact AI
License: Apache-2.0
Requires-Python: >=3.10
Requires-Dist: opentelemetry-api<2,>=1.27
Requires-Dist: opentelemetry-sdk<2,>=1.27
Requires-Dist: opentelemetry-exporter-otlp-proto-http<2,>=1.27
Requires-Dist: opentelemetry-instrumentation-threading<1,>=0.48b0
Requires-Dist: opentelemetry-instrumentation-asgi<1,>=0.48b0
Requires-Dist: opentelemetry-instrumentation-httpx<1,>=0.48b0
Requires-Dist: opentelemetry-instrumentation-azure-aisearch>=0.1.0
Requires-Dist: opentelemetry-instrumentation-openai-v2>=2.1b0
Requires-Dist: opentelemetry-instrumentation-openai>=0.39.3
Requires-Dist: opentelemetry-instrumentation-openai-agents-v2>=0.1.0
Requires-Dist: opentelemetry-instrumentation-google-genai>=0.4b0
Requires-Dist: opentelemetry-instrumentation-vertexai>=0.46.0
Requires-Dist: azure-ai-inference>=1.0.0b9
Requires-Dist: opentelemetry-instrumentation-botocore>=0.45.0b
Requires-Dist: opentelemetry-instrumentation-anthropic>=0.45.0
Requires-Dist: opentelemetry-instrumentation-ollama>=0.45.0
Requires-Dist: opentelemetry-instrumentation-mistralai>=0.45.0
Requires-Dist: opentelemetry-instrumentation-cohere>=0.45.0
Requires-Dist: opentelemetry-instrumentation-groq>=0.45.0
Requires-Dist: opentelemetry-instrumentation-llamaindex>=0.45.0
